Metadata-Version: 1.0
Name: is-palindrom-sham
Version: 0.0.1
Summary: This is a palindrome checking function.
Home-page: https://balajibetadur.github.io
Author: Shashwat Mishra
Author-email: UNKNOWN
License: MIT
Keywords: palindrome,python palindrome,palindrome evaluator
Platform: UNKNOWN
